Compiled from "Deligating.java"
class A {
  A();
    Code:
       0: aload_0       
       1: invokespecial #1                  // Method java/lang/Object."<init>":()V
       4: return        
    LineNumberTable:
      line 1: 0

  public void foo();
    Code:
       0: getstatic     #2                  // Field java/lang/System.out:Ljava/io/PrintStream;
       3: ldc           #3                  // String 4
       5: invokevirtual #4                  // Method java/io/PrintStream.println:(Ljava/lang/String;)V
       8: getstatic     #2                  // Field java/lang/System.out:Ljava/io/PrintStream;
      11: ldc           #5                  // String 5
      13: invokevirtual #4                  // Method java/io/PrintStream.println:(Ljava/lang/String;)V
      16: getstatic     #2                  // Field java/lang/System.out:Ljava/io/PrintStream;
      19: ldc           #6                  // String 6
      21: invokevirtual #4                  // Method java/io/PrintStream.println:(Ljava/lang/String;)V
      24: return        
    LineNumberTable:
      line 3: 0
      line 4: 8
      line 5: 16
      line 6: 24
}
